librus_apix/__init__.py
librus_apix/announcements.py
librus_apix/attendance.py
librus_apix/client.py
librus_apix/completed_lessons.py
librus_apix/exceptions.py
librus_apix/grades.py
librus_apix/helpers.py
librus_apix/homework.py
librus_apix/messages.py
librus_apix/notifications.py
librus_apix/schedule.py
librus_apix/student_information.py
librus_apix/timetable.py
librus_apix/urls.py
librus_apix-1.3.1.dist-info/LICENSE
librus_apix-1.3.1.dist-info/METADATA
librus_apix-1.3.1.dist-info/WHEEL
librus_apix-1.3.1.dist-info/top_level.txt
librus_apix-1.3.1.dist-info/RECORD
