Metadata-Version: 2.1
Name: librus-apix
Version: 1.3.1
Summary: Web Scraper for Librus Synergia
Home-page: https://github.com/poroknights/librus-apix
Author: Pascal Jodłowski
License: MIT
Keywords: librus,scraper,api,synergia
Classifier: License :: OSI Approved :: MIT License
Classifier: Intended Audience :: Developers
Classifier: Programming Language :: Python :: 3
Classifier: Programming Language :: Python :: 3.10
License-File: LICENSE
Requires-Dist: requests
Requires-Dist: aiohttp
Requires-Dist: bs4
Requires-Dist: lxml
